bottlecors/__init__.py
bottlecors-0.34.dist-info/METADATA
bottlecors-0.34.dist-info/RECORD
bottlecors-0.34.dist-info/WHEEL
bottlecors-0.34.dist-info/top_level.txt
