Metadata-Version: 2.1
Name: bottlecors
Version: 0.34
Summary: UNKNOWN
Home-page: UNKNOWN
Author: Arjoonn Sharma
License: UNKNOWN
Project-URL: Source, https://github.com/thesage21/bottlecors
Platform: UNKNOWN
Requires-Python: >=3.6
Requires-Dist: bottle
